MANIFEST.in
hr_attendance_demo.xml
hr_attendance_report.xml
hr_attendance_view.xml
res_config_view.xml
setup.py
./__init__.py
./__openerp__.py
./hr_attendance.py
./res_config.py
./report/__init__.py
./report/attendance_by_month.py
./report/attendance_errors.py
./report/timesheet.py
./wizard/__init__.py
./wizard/hr_attendance_bymonth.py
./wizard/hr_attendance_byweek.py
./wizard/hr_attendance_error.py
i18n/ar.po
i18n/bg.po
i18n/bs.po
i18n/ca.po
i18n/cs.po
i18n/da.po
i18n/de.po
i18n/el.po
i18n/en_GB.po
i18n/es.po
i18n/es_AR.po
i18n/es_CL.po
i18n/es_CR.po
i18n/es_EC.po
i18n/es_MX.po
i18n/es_PY.po
i18n/es_VE.po
i18n/et.po
i18n/fi.po
i18n/fr.po
i18n/gl.po
i18n/he.po
i18n/hr.po
i18n/hr_attendance.pot
i18n/hu.po
i18n/id.po
i18n/it.po
i18n/ja.po
i18n/ko.po
i18n/lt.po
i18n/lv.po
i18n/mk.po
i18n/mn.po
i18n/nb.po
i18n/nl.po
i18n/nl_BE.po
i18n/pl.po
i18n/pt.po
i18n/pt_BR.po
i18n/ro.po
i18n/ru.po
i18n/sl.po
i18n/sq.po
i18n/sr.po
i18n/sr@latin.po
i18n/sv.po
i18n/th.po
i18n/tlh.po
i18n/tr.po
i18n/uk.po
i18n/vi.po
i18n/zh_CN.po
i18n/zh_TW.po
images/hr_attendances.jpeg
openerp_hr_attendance.egg-info/PKG-INFO
openerp_hr_attendance.egg-info/SOURCES.txt
openerp_hr_attendance.egg-info/dependency_links.txt
openerp_hr_attendance.egg-info/requires.txt
openerp_hr_attendance.egg-info/top_level.txt
report/attendance_errors.rml
report/attendance_errors.sxw
report/bymonth.xsl
report/hr_custom_default.xsl
report/hr_custom_rml.xsl
report/timesheet.xsl
security/ir.model.access.csv
security/ir_rule.xml
static/src/img/emp-in-disable32.png
static/src/img/emp-in32.png
static/src/img/emp-out-disable32.png
static/src/img/emp-out32.png
static/src/js/attendance.js
static/src/xml/attendance.xml
test/attendance_process.yml
test/hr_attendance_report.yml
wizard/hr_attendance_bymonth_view.xml
wizard/hr_attendance_byweek_view.xml
wizard/hr_attendance_error_view.xml